dc_index/__init__.py
dc_index-0.1.3.dist-info/LICENSE
dc_index-0.1.3.dist-info/METADATA
dc_index-0.1.3.dist-info/WHEEL
dc_index-0.1.3.dist-info/RECORD
