Metadata-Version: 2.1
Name: dc-index
Version: 0.1.3
Summary: 
License: Copyright (C) Merico, Inc. - All Rights Reserved.
